electiersa/__init__.py
electiersa/electiersa.py
electiersa-0.0.1.dist-info/METADATA
electiersa-0.0.1.dist-info/WHEEL
electiersa-0.0.1.dist-info/top_level.txt
electiersa-0.0.1.dist-info/RECORD
