Metadata-Version: 2.1
Name: electiersa
Version: 0.0.1
Summary: Adapted RSA library for university project called Electie
Home-page: UNKNOWN
Author: tim172021@googlegroups.com
Author-email: UNKNOWN
License: MIT
Platform: UNKNOWN
Requires-Dist: pycryptodome
Requires-Dist: pydantic
